<?xml version="1.0" encoding="UTF-8"?>
<ti:app xmlns:ti="http://ti.appcelerator.org">
    <deployment-targets>
        <target device="mobileweb">false</target>
        <target device="iphone">true</target>
        <target device="ipad">true</target>
        <target device="android">true</target>
        <target device="blackberry">false</target>
    </deployment-targets>
    <sdk-version>2.1.3.GA</sdk-version>
    <id>com.att.developer</id>
    <name>ATTTiKitchenSink</name>
    <version>1.0</version>
    <publisher>AT&amp;T API</publisher>
    <url>http://developer.att.com</url>
    <description>not specified</description>
    <copyright>2012 by ATT</copyright>
    <icon>appicon.png</icon>
    <persistent-wifi>false</persistent-wifi>
    <prerendered-icon>false</prerendered-icon>
    <statusbar-style>default</statusbar-style>
    <statusbar-hidden>false</statusbar-hidden>
    <fullscreen>false</fullscreen>
    <navbar-hidden>false</navbar-hidden>
    <analytics>true</analytics>
    <guid>85c4d3c3-f918-4265-aa43-d6017d4cc831</guid>
    <property name="ti.ui.defaultunit">system</property>
    <iphone>
        <orientations device="iphone">
            <orientation>Ti.UI.PORTRAIT</orientation>
        </orientations>
        <orientations device="ipad">
            <orientation>Ti.UI.PORTRAIT</orientation>
            <orientation>Ti.UI.UPSIDE_PORTRAIT</orientation>
            <orientation>Ti.UI.LANDSCAPE_LEFT</orientation>
            <orientation>Ti.UI.LANDSCAPE_RIGHT</orientation>
        </orientations>
    </iphone>
    <android xmlns:android="http://schemas.android.com/apk/res/android">
    	<manifest>
			<supports-screens android:anyDensity="true"/>
		</manifest>
    </android>
    <mobileweb>
        <precache/>
        <splash>
            <enabled>true</enabled>
            <inline-css-images>true</inline-css-images>
        </splash>
        <theme>default</theme>
    </mobileweb>
    <property name="accessKey">place your access key here</property>
    <property name="secretKey">place your secret key here</property>
    <property name="shortCode">place your short code here</property>
    <property name="scope">place your Scope here</property>
    <property name="amount">put your payment amount value</property>
    <property name="description">put your payment description here</property>
    <property name="paymentServerUrl">paymentServerUrl value</property>
    <modules>
        <module platform="commonjs" version="1.0">att</module>
        <module platform="iphone" version="1.0">ti.api.att</module>
        <module platform="android" version="1.0">ti.api.att</module>
    </modules>
</ti:app>
